fiveg_naas_api-1.2.3.data/scripts/fiveg_naas_api
src/__init__.py
src/fiveg_naas_api.py
src/geolocation_api.py
fiveg_naas_api-1.2.3.dist-info/LICENSE
fiveg_naas_api-1.2.3.dist-info/METADATA
fiveg_naas_api-1.2.3.dist-info/WHEEL
fiveg_naas_api-1.2.3.dist-info/top_level.txt
fiveg_naas_api-1.2.3.dist-info/RECORD
