Metadata-Version: 2.1
Name: fiveg-naas-api
Version: 1.2.3
Summary: FiveG Digital N+aaS API package
Home-page: https://github.com/fiveg-digital/fiveg-naas-api
Author: Umut Karabudak
Author-email: umut.karabudak@fiveg.com
License: UNKNOWN
Platform: UNKNOWN
Classifier: Programming Language :: Python :: 3
Classifier: License :: OSI Approved :: MIT License
Classifier: Operating System :: OS Independent
